rpki_as0_bogons/__init__.py
rpki_as0_bogons/slurm.py
rpki_as0_bogons-0.3.1.dist-info/LICENSE
rpki_as0_bogons-0.3.1.dist-info/METADATA
rpki_as0_bogons-0.3.1.dist-info/WHEEL
rpki_as0_bogons-0.3.1.dist-info/entry_points.txt
rpki_as0_bogons-0.3.1.dist-info/top_level.txt
rpki_as0_bogons-0.3.1.dist-info/RECORD
