Metadata-Version: 2.1
Name: rpki-as0-bogons
Version: 0.3.1
Summary: RPKI AS0 Slurm file generator for bogons
Home-page: https://github.com/stucchimax/rpki-as0-bogons
Maintainer: Massimiliano Stucchi
Maintainer-email: max@stucchi.ch
License: BSD
Keywords: rpki prefix routing networking
Platform: UNKNOWN
Classifier: Intended Audience :: Developers
Classifier: Topic :: Software Development :: Libraries :: Python Modules
Classifier: Topic :: System :: Networking
Classifier: License :: OSI Approved :: BSD License
Classifier: Programming Language :: Python :: 3 :: Only
Requires-Dist: requests
